{
    "KPlugin": {
        "Authors": [
            {
                "Email": "hanyoung@protonmail.com",
                "Name": "HanY",
                "Name[ar]": "هان يونغ",
                "Name[bg]": "HanY",
                "Name[ca@valencia]": "HanY",
                "Name[ca]": "HanY",
                "Name[cs]": "HanY",
                "Name[de]": "HanY",
                "Name[en_GB]": "HanY",
                "Name[eo]": "HanY",
                "Name[es]": "HanY",
                "Name[eu]": "HanY",
                "Name[fi]": "HanY",
                "Name[fr]": "HanY",
                "Name[gl]": "HanY",
                "Name[he]": "HanY (האן י)",
                "Name[hu]": "HanY",
                "Name[ia]": "HanY",
                "Name[it]": "HanY",
                "Name[ka]": "HanY",
                "Name[ko]": "HanY",
                "Name[lt]": "HanY",
                "Name[lv]": "HanY",
                "Name[nl]": "HanY",
                "Name[nn]": "HanY",
                "Name[pa]": "ਹਾਂਯੇ",
                "Name[pl]": "HanY",
                "Name[pt]": "HanY",
                "Name[pt_BR]": "HanY",
                "Name[ru]": "HanY",
                "Name[sa]": "हनY",
                "Name[sk]": "HanY",
                "Name[sl]": "HanY",
                "Name[sv]": "HanY",
                "Name[tr]": "HanY",
                "Name[uk]": "HanY",
                "Name[x-test]": "xxHanYxx",
                "Name[zh_CN]": "HanY",
                "Name[zh_TW]": "HanY"
            }
        ],
        "Category": "Utilities",
        "Description": "KClock widget (1x2)",
        "Description[ar]": "ودجة ساعتك (1x2)",
        "Description[bg]": "Уиджет KClock (1x2)",
        "Description[ca@valencia]": "Giny de KClock (1x2)",
        "Description[ca]": "Giny del KClock (1x2)",
        "Description[cs]": "Widget KClock (1x2)",
        "Description[de]": "KClock-Miniprogramm (1x2)",
        "Description[en_GB]": "KClock widget (1x2)",
        "Description[eo]": "KClock-fenestraĵo (1x2)",
        "Description[es]": "Widget de KClock (1x2)",
        "Description[eu]": "KClock trepeta (1x2)",
        "Description[fi]": "KClock-sovelma (1×2)",
        "Description[fr]": "Composant graphique de KClock (1 x 2)",
        "Description[gl]": "Trebello de KClock (1×2)",
        "Description[he]": "וידג׳ט של KClock‏ (‎1×2)",
        "Description[hu]": "KClock felületi elem (1x2-es)",
        "Description[ia]": "KClock widget (1x2)",
        "Description[it]": "Oggetto KClock (1x2)",
        "Description[ka]": "KClock-ის ვიჯეტი (1x2)",
        "Description[ko]": "KClock 위젯(1x2)",
        "Description[lt]": "KClock valdiklis (1x2)",
        "Description[lv]": "„KClock“ logdaļa (1×2)",
        "Description[nl]": "KClock-widget (1x2)",
        "Description[nn]": "KClock-element (1 × 2)",
        "Description[pa]": "ਕੇ-ਘੜੀ ਵਿਜੈਟ (1x2)",
        "Description[pl]": "Element interfejsu KClock (1x2)",
        "Description[pt]": "Elemento do KClock (1x2)",
        "Description[pt_BR]": "Widget do KClock (1x2)",
        "Description[ru]": "Виджет KClock (1x2)",
        "Description[sa]": "KClock विजेट (1x2) 1.1.",
        "Description[sk]": "KClock widget (1x2)",
        "Description[sl]": "KClock gradnik (1x2)",
        "Description[sv]": "Klockkomponent (1x2)",
        "Description[tr]": "K Saat araç takımı (1 × 2)",
        "Description[uk]": "Віджет KClock (1x2)",
        "Description[x-test]": "xxKClock widget (1x2)xx",
        "Description[zh_CN]": "KClock 挂件 (1x2)",
        "Description[zh_TW]": "KClock 元件 (1x2)",
        "EnabledByDefault": true,
        "FormFactors": [
            "tablet",
            "handset",
            "desktop"
        ],
        "Icon": "kclock_plasmoid_1x2",
        "Id": "org.kde.plasma.kclock_1x2",
        "License": "LGPL-2.1+",
        "Name": "KClock_1x2",
        "Name[ar]": "ساعتك_1x2",
        "Name[bg]": "KClock_1x2",
        "Name[ca@valencia]": "KClock_1x2",
        "Name[ca]": "KClock_1x2",
        "Name[cs]": "KClock_1x2",
        "Name[de]": "KClock_1x2",
        "Name[en_GB]": "KClock_1x2",
        "Name[eo]": "KClock_1x2",
        "Name[es]": "KClock_1x2",
        "Name[eu]": "KClock_1x2",
        "Name[fi]": "KClock_1x2",
        "Name[fr]": "KClock_1 x 2",
        "Name[gl]": "KClock_1x2",
        "Name[he]": "KClock_1x2",
        "Name[hu]": "KClock_1x2",
        "Name[ia]": "KClock_1x2",
        "Name[it]": "KClock_1x2",
        "Name[ka]": "KClock_1x2",
        "Name[ko]": "KClock_1x2",
        "Name[lt]": "KClock_1x2",
        "Name[lv]": "KClock_1x2",
        "Name[nl]": "KClock_1x2",
        "Name[nn]": "KClock_1x2",
        "Name[pa]": "ਕੇ-ਘੜੀ_1x2",
        "Name[pl]": "KClock_1x2",
        "Name[pt]": "KClock_1x2",
        "Name[pt_BR]": "KClock_1x2",
        "Name[ru]": "KClock_1x2",
        "Name[sa]": "केघड़ी_1x2",
        "Name[sk]": "KClock_1x2",
        "Name[sl]": "KClock_1x2",
        "Name[sv]": "Klocka 1x2",
        "Name[tr]": "K Saat_1 × 2",
        "Name[uk]": "KClock_1x2",
        "Name[x-test]": "xxKClock_1x2xx",
        "Name[zh_CN]": "KClock_1x2",
        "Name[zh_TW]": "KClock_1x2",
        "ServiceTypes": [
            "Plasma/Applet"
        ],
        "Version": "1.0",
        "Website": "https://apps.kde.org/kclock"
    },
    "X-Plasma-API": "declarativeappletscript",
    "X-Plasma-DBusActivationService": "org.kde.kclock.*",
    "X-Plasma-MainScript": "ui/main.qml",
    "X-Plasma-NotificationArea": "true",
    "X-Plasma-NotificationAreaCategory": "ApplicationStatus",
    "X-Plasma-Provides": [
        "org.kde.plasma.time"
    ]
}
